README.md
setup.py
meta/__init__.py
meta/metaenv/__init__.py
meta/metaenv/create_env.py
meta/metalog/__init__.py
meta/metalog/apps.py
meta/metalog/decorator.py
meta/metalog/log_storage.py
meta/metalog/models.py
meta/metalog/migrations/0001_initial.py
meta/metalog/migrations/__init__.py
meta/metaviews/__init__.py
meta/metaviews/decorator.py
meta/metaviews/metatypes.py
meta/metaviews/views.py
meta/metaviews/data_generation/__init__.py
meta/metaviews/data_generation/data_factory.py
meta/metaviews/data_generation/datatable_factory.py
meta/metaviews/data_generation/detail_factory.py
meta/metaviews/data_generation/edit_factory.py
meta/metaviews/data_generation/filters_factory.py
meta/metaviews/data_generation/form_factory.py
meta/metaviews/data_generation/wlist_factory.py
metabootstrap.egg-info/PKG-INFO
metabootstrap.egg-info/SOURCES.txt
metabootstrap.egg-info/dependency_links.txt
metabootstrap.egg-info/entry_points.txt
metabootstrap.egg-info/requires.txt
metabootstrap.egg-info/top_level.txt