Metadata-Version: 2.1
Name: metabootstrap
Version: 1.0.20
Summary: Apis for Django Rest Framework made for Webix clients
Home-page: https://bitbucket.org/isnstudio/metabootstrap/src/master/
Author: ISN Studio
Project-URL: Source, https://bitbucket.org/isnstudio/metabootstrap/src/master/
Requires-Python: >=3.8
